idun_guardian_sdk/__init__.py
idun_guardian_sdk/constants.py
idun_guardian_sdk/debug_logs.py
idun_guardian_sdk/event.py
idun_guardian_sdk/event_handlers.py
idun_guardian_sdk/exceptions.py
idun_guardian_sdk/guardian_ble.py
idun_guardian_sdk/guardian_client.py
idun_guardian_sdk/guardian_http_api.py
idun_guardian_sdk/guardian_recording.py
idun_guardian_sdk/polling_service.py
idun_guardian_sdk/types.py
idun_guardian_sdk/utils.py
idun_guardian_sdk/websocket_messages.py
idun_guardian_sdk/ws_msg_handler.py
idun_guardian_sdk-0.1.20.dist-info/METADATA
idun_guardian_sdk-0.1.20.dist-info/WHEEL
idun_guardian_sdk-0.1.20.dist-info/RECORD
