Metadata-Version: 2.3
Name: idun-guardian-sdk
Version: 0.1.20
Summary: 
License: Proprietary
Author: IDUN Technologies AG
Author-email: support@iduntechnologies.com
Requires-Python: >=3.9,<3.14
Classifier: License :: Other/Proprietary License
Classifier: Programming Language :: Python :: 3
Classifier: Programming Language :: Python :: 3.9
Classifier: Programming Language :: Python :: 3.10
Classifier: Programming Language :: Python :: 3.11
Classifier: Programming Language :: Python :: 3.12
Classifier: Programming Language :: Python :: 3.13
Requires-Dist: bleak (>=0.21.1,<0.22.4)
Requires-Dist: certifi (>=2024.2.2,<2025.0.0)
Requires-Dist: pycryptodome (>=3.20.0,<4.0.0)
Requires-Dist: pylsl (>=1.16.2,<2.0.0)
Requires-Dist: python-dotenv (>=1.0.1,<2.0.0)
Requires-Dist: requests (>=2.31.0,<3.0.0)
Requires-Dist: urllib3 (<2.0)
Requires-Dist: websockets (>=12.0,<13.0)
